dvd_weather/__init__.py
dvd_weather/weather.py
dvd_weather_weather-1.3.dist-info/METADATA
dvd_weather_weather-1.3.dist-info/WHEEL
dvd_weather_weather-1.3.dist-info/top_level.txt
dvd_weather_weather-1.3.dist-info/RECORD
