Metadata-Version: 2.1
Name: dvd-weather-weather
Version: 1.3
Summary: look at the py project, it is easy
Home-page: UNKNOWN
Author: DD
Author-email: d.avid-5@qq.com
License: UNKNOWN
Platform: UNKNOWN
